[
  {
    "id": "src.main",
    "name": "main",
    "stats": {
      "size": 190851,
      "gzipSize": 50113
    }
  },
  {
    "id": "node_modules.main",
    "name": "node_modules [main]",
    "stats": {
      "size": 198763,
      "gzipSize": 59337
    }
  },
  {
    "id": "node_modules.async",
    "name": "node_modules [async]",
    "stats": {
      "size": 21129,
      "gzipSize": 6119
    }
  },
  {
    "id": "atlaskit.core.main",
    "name": "main",
    "stats": {
      "size": 261137,
      "gzipSize": 56669
    }
  },
  {
    "id": "atlaskit.core.async",
    "name": "async",
    "stats": {
      "size": 21101,
      "gzipSize": 5965
    }
  },
  {
    "id": "atlaskit.elements.main",
    "name": "main",
    "stats": {
      "size": 2064,
      "gzipSize": 920
    }
  },
  {
    "id": "atlaskit.search.main",
    "name": "main",
    "stats": {
      "size": 17894,
      "gzipSize": 4518
    }
  },
  {
    "id": "combined.main",
    "name": "main",
    "stats": {
      "size": 664798,
      "gzipSize": 172899
    }
  },
  {
    "id": "combined.async",
    "name": "async",
    "stats": {
      "size": 42170,
      "gzipSize": 11501
    }
  }
]